Metadata-Version: 2.1
Name: odoo10-addon-purchase-tier-validation
Version: 10.0.1.0.0.99.dev4
Summary: Extends the functionality of Purchase Orders to support a tier validation process.
Home-page: https://github.com/OCA/purchase-workflow
Author: Eficent, Odoo Community Association (OCA)
Author-email: support@odoo-community.org
License: AGPL-3
Platform: UNKNOWN
Classifier: Programming Language :: Python
Classifier: Framework :: Odoo
Classifier: License :: OSI Approved :: GNU Affero General Public License v3
Requires-Python: ~=2.7
Requires-Dist: odoo10-addon-base-tier-validation
Requires-Dist: odoo (<10.1dev,>=10.0)
